earsegmentationai/__init__.py
earsegmentationai/__version__.py
earsegmentationai/api/__init__.py
earsegmentationai/api/base.py
earsegmentationai/api/image.py
earsegmentationai/api/video.py
earsegmentationai/cli/__init__.py
earsegmentationai/cli/app.py
earsegmentationai/compat.py
earsegmentationai/core/__init__.py
earsegmentationai/core/config.py
earsegmentationai/core/model.py
earsegmentationai/core/predictor.py
earsegmentationai/postprocessing/__init__.py
earsegmentationai/postprocessing/visualization.py
earsegmentationai/preprocessing/__init__.py
earsegmentationai/preprocessing/transforms.py
earsegmentationai/preprocessing/validators.py
earsegmentationai/utils/__init__.py
earsegmentationai/utils/exceptions.py
earsegmentationai/utils/logging.py
earsegmentationai-2.0.0.dist-info/LICENSE
earsegmentationai-2.0.0.dist-info/METADATA
earsegmentationai-2.0.0.dist-info/WHEEL
earsegmentationai-2.0.0.dist-info/entry_points.txt
earsegmentationai-2.0.0.dist-info/RECORD
