Metadata-Version: 2.1
Name: earsegmentationai
Version: 2.0.0
Summary: Pytorch Based - Efficient and Lightweight Ear Segmentation
Home-page: https://github.com/umitkacar/Ear-segmentation-ai
Keywords: pytorch,ear,segmentation,ear-segmentation,segmentation_models,ear detection,detection
Author: Umit KACAR
Author-email: umitkacar.phd@gmail.com
Maintainer: Umit KACAR
Maintainer-email: umitkacar.phd@gmail.com
Requires-Python: >=3.8,<3.11
Classifier: Development Status :: 4 - Beta
Classifier: Environment :: X11 Applications
Classifier: License :: OSI Approved :: MIT License
Classifier: Natural Language :: English
Classifier: Operating System :: OS Independent
Classifier: Programming Language :: Python :: 3
Classifier: Programming Language :: Python :: 3.8
Classifier: Programming Language :: Python :: 3.9
Classifier: Programming Language :: Python :: 3.10
Requires-Dist: albumentations (>=1.3.0,<2.0.0)
Requires-Dist: click (>=8.1.3,<9.0.0)
Requires-Dist: colorama (>=0.4.6,<0.5.0)
Requires-Dist: commonmark (>=0.9.1,<0.10.0)
Requires-Dist: imgviz (>=1.7.2,<2.0.0)
Requires-Dist: numpy (==1.24.1)
Requires-Dist: opencv-python (>=4.6.0.66,<5.0.0.0)
Requires-Dist: pillow (==9.3.0)
Requires-Dist: poethepoet (>=0.18.1,<0.19.0)
Requires-Dist: pygments (>=2.14.0,<3.0.0)
Requires-Dist: requests (>=2.28.2,<3.0.0)
Requires-Dist: rich (>=13.3.1,<14.0.0)
Requires-Dist: segmentation-models-pytorch (>=0.3.2,<0.4.0)
Requires-Dist: shellingham (>=1.5.0.post1,<2.0.0)
Requires-Dist: torch (>=1.13.1,<2.0.0)
Requires-Dist: torchvision (>=0.14.1,<0.15.0)
Requires-Dist: tqdm (>=4.65.0,<5.0.0)
Requires-Dist: typer (>=0.7.0,<0.8.0)
Project-URL: Documentation, https://github.com/umitkacar/Ear-segmentation-ai/tree/main/docs
Project-URL: Repository, https://github.com/umitkacar/Ear-segmentation-ai
